{
  "classificationDefs": [
  ],
  "structDefs": [
  ],
  "entityDefs": [
    {
      "superTypes": ["DataSet"],
      "serviceType": "file_system",
      "category": "ENTITY",
      "name": "ftp_file",
      "description": "a type definition for a file which contains data, this could a file that needs to be processed or it can be an output (ex: extracts)",
      "typeVersion": "1.0",
      "attributeDefs": [
        {
          "name": "file_directory",
          "typeName": "string",
          "isOptional": false,
          "cardinality": "SINGLE",
          "valuesMinCount": 1,
          "valuesMaxCount": 1,
          "isUnique": false,
          "isIndexable": true
        },
        {
          "name": "frequency",
          "typeName": "string",
          "isOptional": false,
          "cardinality": "SINGLE",
          "valuesMinCount": 1,
          "valuesMaxCount": 1,
          "isUnique": false,
          "isIndexable": false
        },
        {
          "name": "group",
          "typeName": "string",
          "isOptional": false,
          "cardinality": "SINGLE",
          "valuesMinCount": 1,
          "valuesMaxCount": 1,
          "isUnique": false,
          "isIndexable": false
        },
        {
          "name": "format",
          "typeName": "string",
          "isOptional": false,
          "cardinality": "SINGLE",
          "valuesMinCount": 1,
          "valuesMaxCount": 1,
          "isUnique": false,
          "isIndexable": false
        },
        {
          "name": "ftp_server",
          "typeName": "string",
          "isOptional": false,
          "cardinality": "SINGLE",
          "valuesMinCount": 1,
          "valuesMaxCount": 1,
          "isUnique": false,
          "isIndexable": false
        },
        {
          "name": "col_schema",
          "typeName": "array<ftp_file_column>",
          "isOptional": true,
          "cardinality": "SINGLE",
          "valuesMinCount": 1,
          "valuesMaxCount": 1,
          "isUnique": false,
          "isIndexable": false
        }
      ]
    },
    {
            "name": "ftp_file_column",
            "description": "a column in an ftp_file name",
            "superTypes": ["DataSet"],
            "serviceType": "file_system",
            "typeVersion": "1.2",
            "options": {
              "schemaAttributes": "[\"name\", \"description\", \"owner\", \"data_type\", \"comment\", \" isPrimaryKey\", \" isNullable\"]"
            },
            "attributeDefs": [
                {
                    "name": "data_type",
                    "typeName": "string",
                    "isOptional": true,
                    "cardinality": "SINGLE",
                    "isUnique": false,
                    "isIndexable": true
                },
                {
                    "name": "length",
                    "typeName": "int",
                    "isOptional": true,
                    "cardinality": "SINGLE",
                    "isUnique": false,
                    "isIndexable": false
                },
                {
                    "name": "default_value",
                    "typeName": "string",
                    "isOptional": true,
                    "cardinality": "SINGLE",
                    "isUnique": false,
                    "isIndexable": false
                },
                {
                    "name": "comment",
                    "typeName": "string",
                    "isOptional": true,
                    "cardinality": "SINGLE",
                    "isUnique": false,
                    "isIndexable": false
                },
                {
                    "name": "isNullable",
                    "typeName": "boolean",
                    "isOptional": true,
                    "cardinality": "SINGLE",
                    "isUnique": false,
                    "isIndexable": false
                },
                {
                    "name": "isPrimaryKey",
                    "typeName": "boolean",
                    "isOptional": true,
                    "cardinality": "SINGLE",
                    "isUnique": false,
                    "isIndexable": false
                }
            ]
        }
  ]
}
